sqlitepro/__init__.py
sqlitepro/sqlite3.dll
sqlitepro/sqlitepro.py
sqlpro-1.0.1.dist-info/METADATA
sqlpro-1.0.1.dist-info/WHEEL
sqlpro-1.0.1.dist-info/top_level.txt
sqlpro-1.0.1.dist-info/RECORD
