Metadata-Version: 2.1
Name: sqlpro
Version: 1.0.1
Summary: The simple sqlite3 library supports encrypted files and querying data
Home-page: UNKNOWN
License: UNKNOWN
Platform: UNKNOWN
